{
  "gitSyncId": "6a0a1bde3214f344228346e7_449b3d4f-c23d-4723-a373-fe9ce31b7a6b",
  "id": "Events_evtSave.componentSnapshot",
  "pluginId": "js-plugin",
  "pluginType": "JS",
  "unpublishedAction": {
    "actionConfiguration": {
      "encodeParamsToggle": true,
      "jsArguments": [
        {
          "name": "rows"
        }
      ],
      "paginationType": "NONE",
      "timeoutInMillisecond": 10000
    },
    "collectionId": "Events_evtSave",
    "confirmBeforeExecute": false,
    "datasource": {
      "isAutoGenerated": false,
      "name": "UNUSED_DATASOURCE",
      "pluginId": "js-plugin"
    },
    "dynamicBindingPathList": [
      {
        "key": "body"
      }
    ],
    "fullyQualifiedName": "evtSave.componentSnapshot",
    "name": "componentSnapshot",
    "pageId": "Events",
    "runBehaviour": "MANUAL",
    "userSetOnLoad": false
  }
}