{
  "gitSyncId": "6a0a1bde3214f344228346e7_2b7dcb75-7142-4976-9a49-0993e3cd2065",
  "id": "Dish_dshCompTable.componentDietTagSummary",
  "pluginId": "js-plugin",
  "pluginType": "JS",
  "unpublishedAction": {
    "actionConfiguration": {
      "encodeParamsToggle": true,
      "jsArguments": [],
      "paginationType": "NONE",
      "timeoutInMillisecond": 10000
    },
    "collectionId": "Dish_dshCompTable",
    "confirmBeforeExecute": false,
    "datasource": {
      "isAutoGenerated": false,
      "name": "UNUSED_DATASOURCE",
      "pluginId": "js-plugin"
    },
    "dynamicBindingPathList": [
      {
        "key": "body"
      }
    ],
    "fullyQualifiedName": "dshCompTable.componentDietTagSummary",
    "name": "componentDietTagSummary",
    "pageId": "Dish",
    "runBehaviour": "MANUAL",
    "userSetOnLoad": false
  }
}