{
  "animateLoading": true,
  "borderRadius": "{{appsmith.theme.borderRadius.appBorderRadius}}",
  "bottomRow": 8,
  "dynamicBindingPathList": [
    {
      "key": "truncateButtonColor"
    },
    {
      "key": "fontFamily"
    },
    {
      "key": "borderRadius"
    },
    {
      "key": "text"
    }
  ],
  "dynamicHeight": "AUTO_HEIGHT",
  "dynamicTriggerPathList": [],
  "fontFamily": "{{appsmith.theme.fontFamily.appFont}}",
  "fontSize": "1rem",
  "fontStyle": "BOLD",
  "isLoading": false,
  "isVisible": true,
  "key": "31je6kj7ki",
  "leftColumn": 0,
  "maxDynamicHeight": 9000,
  "minDynamicHeight": 4,
  "minWidth": 450,
  "mobileBottomRow": 9,
  "mobileLeftColumn": 0,
  "mobileRightColumn": 16,
  "mobileTopRow": 5,
  "needsErrorInfo": false,
  "originalBottomRow": 8,
  "originalTopRow": 4,
  "overflow": "NONE",
  "parentColumnSpace": 6.021484375,
  "parentId": "i21lqbi2r0",
  "parentRowSpace": 10,
  "renderMode": "CANVAS",
  "responsiveBehavior": "fill",
  "rightColumn": 63,
  "shouldTruncate": false,
  "text": "{{\n  \"Contact: \" +\n  (getSelectedQuote.data?.[0]?.venue_contact || \"\")\n}}",
  "textAlign": "LEFT",
  "textColor": "#231F20",
  "topRow": 4,
  "truncateButtonColor": "{{appsmith.theme.colors.primaryColor}}",
  "type": "TEXT_WIDGET",
  "version": 1,
  "widgetId": "34porhyhq0",
  "widgetName": "txtQuoVnuContact"
}