{
  "gitSyncId": "6a0a1bde3214f344228346e7_051674e2-0e88-4b83-9ef8-f396f0eda9b4",
  "id": "Order_updGroOrderPackaging",
  "pluginId": "postgres-plugin",
  "pluginType": "DB",
  "unpublishedAction": {
    "actionConfiguration": {
      "body": "update public.gro_order\nset\n  packaging_id = {{\n    appsmith.store.current_packaging_id === \"\" ||\n    appsmith.store.current_packaging_id == null\n      ? null\n      : Number(appsmith.store.current_packaging_id)\n  }},\n  updated_at = now()\nwhere id = {{ Number(appsmith.store.current_gro_order_id || 0) }}\n  and client_id = '{{ appsmith.store.current_client_id }}'::uuid\nreturning id, packaging_id;",
      "encodeParamsToggle": true,
      "paginationType": "NONE",
      "pluginSpecifiedTemplates": [
        {
          "value": true
        }
      ],
      "timeoutInMillisecond": 10000
    },
    "confirmBeforeExecute": false,
    "datasource": {
      "id": "FoodCostingDB",
      "isAutoGenerated": false,
      "name": "FoodCostingDB",
      "pluginId": "postgres-plugin"
    },
    "dynamicBindingPathList": [
      {
        "key": "body"
      }
    ],
    "name": "updGroOrderPackaging",
    "pageId": "Order",
    "runBehaviour": "MANUAL",
    "userSetOnLoad": false
  }
}