{
  "gitSyncId": "6a0a1bde3214f344228346e7_d0b782e9-10b8-49d2-b3d7-f66784face22",
  "id": "Menu_mnuCompTable.itemKey",
  "pluginId": "js-plugin",
  "pluginType": "JS",
  "unpublishedAction": {
    "actionConfiguration": {
      "encodeParamsToggle": true,
      "jsArguments": [
        {
          "name": "row"
        }
      ],
      "paginationType": "NONE",
      "timeoutInMillisecond": 10000
    },
    "collectionId": "Menu_mnuCompTable",
    "confirmBeforeExecute": false,
    "datasource": {
      "isAutoGenerated": false,
      "name": "UNUSED_DATASOURCE",
      "pluginId": "js-plugin"
    },
    "dynamicBindingPathList": [
      {
        "key": "body"
      }
    ],
    "fullyQualifiedName": "mnuCompTable.itemKey",
    "name": "itemKey",
    "pageId": "Menu",
    "runBehaviour": "MANUAL",
    "userSetOnLoad": false
  }
}