{
  "gitSyncId": "6a0a1bde3214f344228346e7_89092feb-483c-4592-af1a-5c7548202922",
  "id": "Quotation_assignQuoVenue",
  "pluginId": "postgres-plugin",
  "pluginType": "DB",
  "unpublishedAction": {
    "actionConfiguration": {
      "body": "update public.quo_events qe\nset\n  venue_id = nullif(\n    {{ Number(selQuoVenue.selectedOptionValue || 0) }},\n    0\n  )::bigint,\n\n  venue_instructions = case\n    when {{ Number(selQuoVenue.selectedOptionValue || 0) }} > 0\n      then (\n        select v.generic_notes\n        from public.venues v\n        where v.id = {{ Number(selQuoVenue.selectedOptionValue || 0) }}::bigint\n          and v.client_id = qe.client_id\n          and coalesce(v.deleted, false) = false\n      )\n    else null\n  end,\n\n  updated_at = now()\nwhere qe.id = {{ Number(appsmith.store.selectedQuoteEventId || 0) }}::bigint\n  and qe.client_id = '{{ appsmith.store.current_client_id }}'::uuid\n  and coalesce(qe.deleted, false) = false\nreturning\n  qe.id as quote_event_id,\n  qe.venue_id,\n  qe.venue_instructions;",
      "encodeParamsToggle": true,
      "paginationType": "NONE",
      "pluginSpecifiedTemplates": [
        {
          "value": true
        }
      ],
      "timeoutInMillisecond": 10000
    },
    "confirmBeforeExecute": false,
    "datasource": {
      "id": "FoodCostingDB",
      "isAutoGenerated": false,
      "name": "FoodCostingDB",
      "pluginId": "postgres-plugin"
    },
    "dynamicBindingPathList": [
      {
        "key": "body"
      }
    ],
    "name": "assignQuoVenue",
    "pageId": "Quotation",
    "runBehaviour": "MANUAL",
    "userSetOnLoad": false
  }
}